Description
LICENSE
MANIFEST.in
README.rst
ReleaseNotes
apt_install_deps
install.sh
manifest.py
pyformex.desktop
setup.cfg
setup.py
pyformex/__init__.py
pyformex/__main__.py
pyformex/adjacency.py
pyformex/apps.py
pyformex/arraytools.py
pyformex/attributes.py
pyformex/candy.py
pyformex/cmdtools.py
pyformex/collection.py
pyformex/colors.py
pyformex/config.py
pyformex/connectivity.py
pyformex/coords.py
pyformex/coordsys.py
pyformex/core.py
pyformex/curve.py
pyformex/database.py
pyformex/elements.py
pyformex/field.py
pyformex/fileread.py
pyformex/filewrite.py
pyformex/flatkeydb.py
pyformex/formex.py
pyformex/geometry.py
pyformex/geomfile.py
pyformex/geomtools.py
pyformex/inertia.py
pyformex/lazy.py
pyformex/main.py
pyformex/mesh.py
pyformex/messages.py
pyformex/multi.py
pyformex/mydict.py
pyformex/olist.py
pyformex/options.py
pyformex/path.py
pyformex/polygons.py
pyformex/process.py
pyformex/project.py
pyformex/py2rst.py
pyformex/pyformex
pyformex/pyformexrc
pyformex/pzffile.py
pyformex/script.py
pyformex/sendmail.py
pyformex/simple.py
pyformex/software.py
pyformex/timer.py
pyformex/track.py
pyformex/trisurface.py
pyformex/utils.py
pyformex/varray.py
pyformex/appsdir/Core.py
pyformex/appsdir/DicomViewer.py
pyformex/appsdir/FeEx.py
pyformex/appsdir/Hesperia.py
pyformex/appsdir/RunAll.py
pyformex/appsdir/__init__.py
pyformex/bin/listtree.py
pyformex/bin/read_abq_inp.awk
pyformex/data/README
pyformex/data/benedict_6.jpg
pyformex/data/bifurcation.off.gz
pyformex/data/blippo.pgf
pyformex/data/blippok.ttf
pyformex/data/butterfly.png
pyformex/data/hesperia-nieve.prop
pyformex/data/horse.off
pyformex/data/horse.pgf
pyformex/data/image_not_loaded.png
pyformex/data/man.off
pyformex/data/man.pgf
pyformex/data/mark_cross.png
pyformex/data/materials.json
pyformex/data/sections.json
pyformex/data/splines.pgf
pyformex/data/supershape.txt
pyformex/data/teapot1.off
pyformex/data/template.py
pyformex/data/world.jpg
pyformex/doc/Description
pyformex/doc/LICENSE
pyformex/doc/README.rst
