Metadata-Version: 1.1
Name: pyformex
Version: 3.3
Summary: Python framework to create, transform, manipulate and render 3D geometry
Home-page: http://pyformex.org
Author: Benedict Verhegghe
Author-email: bverheg@gmail.com
License: GNU General Public License (GPL)
Download-URL: http://download.savannah.gnu.org/releases/pyformex/pyformex-3.3.tar.gz
Platform: UNKNOWN
Classifier: Development Status :: 4 - Beta
Classifier: Environment :: Console
Classifier: Environment :: X11 Applications :: Qt
Classifier: Intended Audience :: End Users/Desktop
Classifier: Intended Audience :: Science/Research
Classifier: Intended Audience :: Education
Classifier: License :: OSI Approved :: GNU General Public License (GPL)
Classifier: Operating System :: POSIX :: Linux
Classifier: Operating System :: POSIX
Classifier: Operating System :: OS Independent
Classifier: Programming Language :: Python
Classifier: Programming Language :: C
Classifier: Topic :: Multimedia :: Graphics :: 3D Modeling
Classifier: Topic :: Multimedia :: Graphics :: 3D Rendering
Classifier: Topic :: Scientific/Engineering :: Mathematics
Classifier: Topic :: Scientific/Engineering :: Visualization
Classifier: Topic :: Scientific/Engineering :: Physics
